pagefind_bin/__init__.py
pagefind_bin/__main__.py
pagefind_bin/pagefind
pagefind_bin-1.4.0.dist-info/METADATA
pagefind_bin-1.4.0.dist-info/WHEEL
pagefind_bin-1.4.0.dist-info/RECORD
