Metadata-Version: 2.1
Name: pagefind_bin
Version: 1.4.0
Summary:
License: MIT
Author: Pagefind
Classifier: License :: OSI Approved :: MIT License
Classifier: Development Status :: 3 - Alpha
Classifier: Intended Audience :: Developers
Project-URL: Homepage, https://pagefind.app
Project-URL: Source Code, https://github.com/pagefind/pagefind/
Project-URL: Bug Tracker, https://github.com/pagefind/pagefind//issues
Requires-Python: ~=3.9
